Metadata-Version: 2.1
Name: birdvoxpaint
Version: 0.2.2
Summary: Bird Vox False-Color Spectrograms
Author: Phincho Sherpa, Vincent Lostanlen, Bea Steers
Author-email: vincent.lostanlen@cnrs.fr
License: MIT License
Keywords: acoustic detection bird calls fault identification false color spectrogram librosa
License-File: LICENSE
